sqlep/__init__.py
sqlep/settings.py
sqlep/testing.py
sqlep/utils.py
sqlep/runners/__init__.py
sqlep/runners/hive.py
sqlep/runners/query_runner.py
tests/__init__.py
tests/conftest.py
tests/test_testing.py
tests/test_utils.py
tests/utils.py
tests/runners/__init__.py
tests/runners/test_hive.py
sqlep-0.0.1.dist-info/METADATA
sqlep-0.0.1.dist-info/WHEEL
sqlep-0.0.1.dist-info/top_level.txt
sqlep-0.0.1.dist-info/RECORD
